{"type": "directory", "dataset_id": "83b73949-b6c3-4b2b-81b2-cc3f7236a048", "dataset_version": "eb38ea8ece37da4ee1b2037aec3c894dc7e9e145", "children": [{"type": "file", "dataset_id": "83b73949-b6c3-4b2b-81b2-cc3f7236a048", "dataset_version": "eb38ea8ece37da4ee1b2037aec3c894dc7e9e145", "metadata_sources": {"key_source_map": {}, "sources": [{"source_name": "manual_addition", "source_version": "0.1.0", "source_parameter": {}, "source_time": 1714777729.312107, "agent_name": "Micha\u0142 Szczepanik", "agent_email": "m.szczepanik@fz-juelich.de"}]}, "path": "input/MRI/processed/sub-61/ses-2/func/SB61_1_2_20171113_093821.10.1.nii", "contentbytesize": 30966112, "name": "SB61_1_2_20171113_093821.10.1.nii"}, {"type": "file", "dataset_id": "83b73949-b6c3-4b2b-81b2-cc3f7236a048", "dataset_version": "eb38ea8ece37da4ee1b2037aec3c894dc7e9e145", "metadata_sources": {"key_source_map": {}, "sources": [{"source_name": "manual_addition", "source_version": "0.1.0", "source_parameter": {}, "source_time": 1714777729.312107, "agent_name": "Micha\u0142 Szczepanik", "agent_email": "m.szczepanik@fz-juelich.de"}]}, "path": "input/MRI/processed/sub-61/ses-2/func/SB61_1_2_20171113_093821.10.1.nii.gz", "contentbytesize": 20224984, "name": "SB61_1_2_20171113_093821.10.1.nii.gz"}, {"type": "file", "dataset_id": "83b73949-b6c3-4b2b-81b2-cc3f7236a048", "dataset_version": "eb38ea8ece37da4ee1b2037aec3c894dc7e9e145", "metadata_sources": {"key_source_map": {}, "sources": [{"source_name": "manual_addition", "source_version": "0.1.0", "source_parameter": {}, "source_time": 1714777729.312107, "agent_name": "Micha\u0142 Szczepanik", "agent_email": "m.szczepanik@fz-juelich.de"}]}, "path": "input/MRI/processed/sub-61/ses-2/func/SB61_1_2_20171113_093821.6.1.nii.gz", "contentbytesize": 974604, "name": "SB61_1_2_20171113_093821.6.1.nii.gz"}, {"type": "file", "dataset_id": "83b73949-b6c3-4b2b-81b2-cc3f7236a048", "dataset_version": "eb38ea8ece37da4ee1b2037aec3c894dc7e9e145", "metadata_sources": {"key_source_map": {}, "sources": [{"source_name": "manual_addition", "source_version": "0.1.0", "source_parameter": {}, "source_time": 1714777729.312107, "agent_name": "Micha\u0142 Szczepanik", "agent_email": "m.szczepanik@fz-juelich.de"}]}, "path": "input/MRI/processed/sub-61/ses-2/func/SB61_1_2_20171113_093821.7.1.nii.gz", "contentbytesize": 1280365, "name": "SB61_1_2_20171113_093821.7.1.nii.gz"}, {"type": "file", "dataset_id": "83b73949-b6c3-4b2b-81b2-cc3f7236a048", "dataset_version": "eb38ea8ece37da4ee1b2037aec3c894dc7e9e145", "metadata_sources": {"key_source_map": {}, "sources": [{"source_name": "manual_addition", "source_version": "0.1.0", "source_parameter": {}, "source_time": 1714777729.312107, "agent_name": "Micha\u0142 Szczepanik", "agent_email": "m.szczepanik@fz-juelich.de"}]}, "path": "input/MRI/processed/sub-61/ses-2/func/SB61_1_2_20171113_093821.9.1.nii.gz", "contentbytesize": 20181588, "name": "SB61_1_2_20171113_093821.9.1.nii.gz"}, {"type": "file", "dataset_id": "83b73949-b6c3-4b2b-81b2-cc3f7236a048", "dataset_version": "eb38ea8ece37da4ee1b2037aec3c894dc7e9e145", "metadata_sources": {"key_source_map": {}, "sources": [{"source_name": "manual_addition", "source_version": "0.1.0", "source_parameter": {}, "source_time": 1714777729.312107, "agent_name": "Micha\u0142 Szczepanik", "agent_email": "m.szczepanik@fz-juelich.de"}]}, "path": "input/MRI/processed/sub-61/ses-2/func/SB61_1_2_20171113_093821.conc.nii", "contentbytesize": 60457312, "name": "SB61_1_2_20171113_093821.conc.nii"}, {"type": "file", "dataset_id": "83b73949-b6c3-4b2b-81b2-cc3f7236a048", "dataset_version": "eb38ea8ece37da4ee1b2037aec3c894dc7e9e145", "metadata_sources": {"key_source_map": {}, "sources": [{"source_name": "manual_addition", "source_version": "0.1.0", "source_parameter": {}, "source_time": 1714777729.312107, "agent_name": "Micha\u0142 Szczepanik", "agent_email": "m.szczepanik@fz-juelich.de"}]}, "path": "input/MRI/processed/sub-61/ses-2/func/SB61_1_2_20171113_093821.conc.nii.gz", "contentbytesize": 38948844, "name": "SB61_1_2_20171113_093821.conc.nii.gz"}, {"type": "file", "dataset_id": "83b73949-b6c3-4b2b-81b2-cc3f7236a048", "dataset_version": "eb38ea8ece37da4ee1b2037aec3c894dc7e9e145", "metadata_sources": {"key_source_map": {}, "sources": [{"source_name": "manual_addition", "source_version": "0.1.0", "source_parameter": {}, "source_time": 1714777729.312107, "agent_name": "Micha\u0142 Szczepanik", "agent_email": "m.szczepanik@fz-juelich.de"}]}, "path": "input/MRI/processed/sub-61/ses-2/func/SB61_1_2_20171113_093821.conc_bold.nii.gz", "contentbytesize": 38948844, "name": "SB61_1_2_20171113_093821.conc_bold.nii.gz"}, {"type": "file", "dataset_id": "83b73949-b6c3-4b2b-81b2-cc3f7236a048", "dataset_version": "eb38ea8ece37da4ee1b2037aec3c894dc7e9e145", "metadata_sources": {"key_source_map": {}, "sources": [{"source_name": "manual_addition", "source_version": "0.1.0", "source_parameter": {}, "source_time": 1714777729.312107, "agent_name": "Micha\u0142 Szczepanik", "agent_email": "m.szczepanik@fz-juelich.de"}]}, "path": "input/MRI/processed/sub-61/ses-2/func/SB61_1_2_20171113_093821DN.nii.gz", "contentbytesize": 176465, "name": "SB61_1_2_20171113_093821DN.nii.gz"}, {"type": "file", "dataset_id": "83b73949-b6c3-4b2b-81b2-cc3f7236a048", "dataset_version": "eb38ea8ece37da4ee1b2037aec3c894dc7e9e145", "metadata_sources": {"key_source_map": {}, "sources": [{"source_name": "manual_addition", "source_version": "0.1.0", "source_parameter": {}, "source_time": 1714777729.312107, "agent_name": "Micha\u0142 Szczepanik", "agent_email": "m.szczepanik@fz-juelich.de"}]}, "path": "input/MRI/processed/sub-61/ses-2/func/SB61_1_2_20171113_093821Smooth.nii.gz", "contentbytesize": 213683, "name": "SB61_1_2_20171113_093821Smooth.nii.gz"}, {"type": "file", "dataset_id": "83b73949-b6c3-4b2b-81b2-cc3f7236a048", "dataset_version": "eb38ea8ece37da4ee1b2037aec3c894dc7e9e145", "metadata_sources": {"key_source_map": {}, "sources": [{"source_name": "manual_addition", "source_version": "0.1.0", "source_parameter": {}, "source_time": 1714777729.312107, "agent_name": "Micha\u0142 Szczepanik", "agent_email": "m.szczepanik@fz-juelich.de"}]}, "path": "input/MRI/processed/sub-61/ses-2/func/SB61_1_2_20171113_093821SmoothBet.nii-2.nii", "contentbytesize": 590176, "name": "SB61_1_2_20171113_093821SmoothBet.nii-2.nii"}, {"type": "file", "dataset_id": "83b73949-b6c3-4b2b-81b2-cc3f7236a048", "dataset_version": "eb38ea8ece37da4ee1b2037aec3c894dc7e9e145", "metadata_sources": {"key_source_map": {}, "sources": [{"source_name": "manual_addition", "source_version": "0.1.0", "source_parameter": {}, "source_time": 1714777729.312107, "agent_name": "Micha\u0142 Szczepanik", "agent_email": "m.szczepanik@fz-juelich.de"}]}, "path": "input/MRI/processed/sub-61/ses-2/func/SB61_1_2_20171113_093821SmoothBet.nii.gz", "contentbytesize": 49625, "name": "SB61_1_2_20171113_093821SmoothBet.nii.gz"}, {"type": "file", "dataset_id": "83b73949-b6c3-4b2b-81b2-cc3f7236a048", "dataset_version": "eb38ea8ece37da4ee1b2037aec3c894dc7e9e145", "metadata_sources": {"key_source_map": {}, "sources": [{"source_name": "manual_addition", "source_version": "0.1.0", "source_parameter": {}, "source_time": 1714777729.312107, "agent_name": "Micha\u0142 Szczepanik", "agent_email": "m.szczepanik@fz-juelich.de"}]}, "path": "input/MRI/processed/sub-61/ses-2/func/SB61_1_2_20171113_093821SmoothBetMatrixAff.txt", "contentbytesize": 136, "name": "SB61_1_2_20171113_093821SmoothBetMatrixAff.txt"}, {"type": "file", "dataset_id": "83b73949-b6c3-4b2b-81b2-cc3f7236a048", "dataset_version": "eb38ea8ece37da4ee1b2037aec3c894dc7e9e145", "metadata_sources": {"key_source_map": {}, "sources": [{"source_name": "manual_addition", "source_version": "0.1.0", "source_parameter": {}, "source_time": 1714777729.312107, "agent_name": "Micha\u0142 Szczepanik", "agent_email": "m.szczepanik@fz-juelich.de"}]}, "path": "input/MRI/processed/sub-61/ses-2/func/SB61_1_2_20171113_093821SmoothBetMatrixBspline.nii", "contentbytesize": 6184, "name": "SB61_1_2_20171113_093821SmoothBetMatrixBspline.nii"}, {"type": "file", "dataset_id": "83b73949-b6c3-4b2b-81b2-cc3f7236a048", "dataset_version": "eb38ea8ece37da4ee1b2037aec3c894dc7e9e145", "metadata_sources": {"key_source_map": {}, "sources": [{"source_name": "manual_addition", "source_version": "0.1.0", "source_parameter": {}, "source_time": 1714777729.312107, "agent_name": "Micha\u0142 Szczepanik", "agent_email": "m.szczepanik@fz-juelich.de"}]}, "path": "input/MRI/processed/sub-61/ses-2/func/SB61_1_2_20171113_093821SmoothBetMatrixInv.txt", "contentbytesize": 130, "name": "SB61_1_2_20171113_093821SmoothBetMatrixInv.txt"}, {"type": "file", "dataset_id": "83b73949-b6c3-4b2b-81b2-cc3f7236a048", "dataset_version": "eb38ea8ece37da4ee1b2037aec3c894dc7e9e145", "metadata_sources": {"key_source_map": {}, "sources": [{"source_name": "manual_addition", "source_version": "0.1.0", "source_parameter": {}, "source_time": 1714777729.312107, "agent_name": "Micha\u0142 Szczepanik", "agent_email": "m.szczepanik@fz-juelich.de"}]}, "path": "input/MRI/processed/sub-61/ses-2/func/SB61_1_2_20171113_093821SmoothBet_Anno.nii.gz", "contentbytesize": 12937, "name": "SB61_1_2_20171113_093821SmoothBet_Anno.nii.gz"}, {"type": "file", "dataset_id": "83b73949-b6c3-4b2b-81b2-cc3f7236a048", "dataset_version": "eb38ea8ece37da4ee1b2037aec3c894dc7e9e145", "metadata_sources": {"key_source_map": {}, "sources": [{"source_name": "manual_addition", "source_version": "0.1.0", "source_parameter": {}, "source_time": 1714777729.312107, "agent_name": "Micha\u0142 Szczepanik", "agent_email": "m.szczepanik@fz-juelich.de"}]}, "path": "input/MRI/processed/sub-61/ses-2/func/SB61_1_2_20171113_093821SmoothBet_AnnoSplit.nii.gz", "contentbytesize": 14205, "name": "SB61_1_2_20171113_093821SmoothBet_AnnoSplit.nii.gz"}, {"type": "file", "dataset_id": "83b73949-b6c3-4b2b-81b2-cc3f7236a048", "dataset_version": "eb38ea8ece37da4ee1b2037aec3c894dc7e9e145", "metadata_sources": {"key_source_map": {}, "sources": [{"source_name": "manual_addition", "source_version": "0.1.0", "source_parameter": {}, "source_time": 1714777729.312107, "agent_name": "Micha\u0142 Szczepanik", "agent_email": "m.szczepanik@fz-juelich.de"}]}, "path": "input/MRI/processed/sub-61/ses-2/func/SB61_1_2_20171113_093821SmoothBet_AnnoSplit_rsfMRI.nii.gz", "contentbytesize": 9301, "name": "SB61_1_2_20171113_093821SmoothBet_AnnoSplit_rsfMRI.nii.gz"}, {"type": "file", "dataset_id": "83b73949-b6c3-4b2b-81b2-cc3f7236a048", "dataset_version": "eb38ea8ece37da4ee1b2037aec3c894dc7e9e145", "metadata_sources": {"key_source_map": {}, "sources": [{"source_name": "manual_addition", "source_version": "0.1.0", "source_parameter": {}, "source_time": 1714777729.312107, "agent_name": "Micha\u0142 Szczepanik", "agent_email": "m.szczepanik@fz-juelich.de"}]}, "path": "input/MRI/processed/sub-61/ses-2/func/SB61_1_2_20171113_093821SmoothBet_Anno_rsfMRI.nii.gz", "contentbytesize": 8461, "name": "SB61_1_2_20171113_093821SmoothBet_Anno_rsfMRI.nii.gz"}, {"type": "file", "dataset_id": "83b73949-b6c3-4b2b-81b2-cc3f7236a048", "dataset_version": "eb38ea8ece37da4ee1b2037aec3c894dc7e9e145", "metadata_sources": {"key_source_map": {}, "sources": [{"source_name": "manual_addition", "source_version": "0.1.0", "source_parameter": {}, "source_time": 1714777729.312107, "agent_name": "Micha\u0142 Szczepanik", "agent_email": "m.szczepanik@fz-juelich.de"}]}, "path": "input/MRI/processed/sub-61/ses-2/func/SB61_1_2_20171113_093821SmoothBet_AnnorsfMRI.nii.gz", "contentbytesize": 8627, "name": "SB61_1_2_20171113_093821SmoothBet_AnnorsfMRI.nii.gz"}, {"type": "file", "dataset_id": "83b73949-b6c3-4b2b-81b2-cc3f7236a048", "dataset_version": "eb38ea8ece37da4ee1b2037aec3c894dc7e9e145", "metadata_sources": {"key_source_map": {}, "sources": [{"source_name": "manual_addition", "source_version": "0.1.0", "source_parameter": {}, "source_time": 1714777729.312107, "agent_name": "Micha\u0142 Szczepanik", "agent_email": "m.szczepanik@fz-juelich.de"}]}, "path": "input/MRI/processed/sub-61/ses-2/func/SB61_1_2_20171113_093821SmoothBet_IncidenceData.nii.gz", "contentbytesize": 14227448, "name": "SB61_1_2_20171113_093821SmoothBet_IncidenceData.nii.gz"}, {"type": "file", "dataset_id": "83b73949-b6c3-4b2b-81b2-cc3f7236a048", "dataset_version": "eb38ea8ece37da4ee1b2037aec3c894dc7e9e145", "metadata_sources": {"key_source_map": {}, "sources": [{"source_name": "manual_addition", "source_version": "0.1.0", "source_parameter": {}, "source_time": 1714777729.312107, "agent_name": "Micha\u0142 Szczepanik", "agent_email": "m.szczepanik@fz-juelich.de"}]}, "path": "input/MRI/processed/sub-61/ses-2/func/SB61_1_2_20171113_093821SmoothBet_T2w.nii.gz", "contentbytesize": 69501, "name": "SB61_1_2_20171113_093821SmoothBet_T2w.nii.gz"}, {"type": "file", "dataset_id": "83b73949-b6c3-4b2b-81b2-cc3f7236a048", "dataset_version": "eb38ea8ece37da4ee1b2037aec3c894dc7e9e145", "metadata_sources": {"key_source_map": {}, "sources": [{"source_name": "manual_addition", "source_version": "0.1.0", "source_parameter": {}, "source_time": 1714777729.312107, "agent_name": "Micha\u0142 Szczepanik", "agent_email": "m.szczepanik@fz-juelich.de"}]}, "path": "input/MRI/processed/sub-61/ses-2/func/SB61_1_2_20171113_093821SmoothBet_Template.nii.gz", "contentbytesize": 24780, "name": "SB61_1_2_20171113_093821SmoothBet_Template.nii.gz"}, {"type": "file", "dataset_id": "83b73949-b6c3-4b2b-81b2-cc3f7236a048", "dataset_version": "eb38ea8ece37da4ee1b2037aec3c894dc7e9e145", "metadata_sources": {"key_source_map": {}, "sources": [{"source_name": "manual_addition", "source_version": "0.1.0", "source_parameter": {}, "source_time": 1714777729.312107, "agent_name": "Micha\u0142 Szczepanik", "agent_email": "m.szczepanik@fz-juelich.de"}]}, "path": "input/MRI/processed/sub-61/ses-2/func/SB61_1_2_20171113_093821SmoothBet_TemplateAff.nii.gz", "contentbytesize": 73517, "name": "SB61_1_2_20171113_093821SmoothBet_TemplateAff.nii.gz"}, {"type": "file", "dataset_id": "83b73949-b6c3-4b2b-81b2-cc3f7236a048", "dataset_version": "eb38ea8ece37da4ee1b2037aec3c894dc7e9e145", "metadata_sources": {"key_source_map": {}, "sources": [{"source_name": "manual_addition", "source_version": "0.1.0", "source_parameter": {}, "source_time": 1714777729.312107, "agent_name": "Micha\u0142 Szczepanik", "agent_email": "m.szczepanik@fz-juelich.de"}]}, "path": "input/MRI/processed/sub-61/ses-2/func/SB61_1_2_20171113_093821SmoothBet_TemplateAllen.nii.gz", "contentbytesize": 27481, "name": "SB61_1_2_20171113_093821SmoothBet_TemplateAllen.nii.gz"}, {"type": "file", "dataset_id": "83b73949-b6c3-4b2b-81b2-cc3f7236a048", "dataset_version": "eb38ea8ece37da4ee1b2037aec3c894dc7e9e145", "metadata_sources": {"key_source_map": {}, "sources": [{"source_name": "manual_addition", "source_version": "0.1.0", "source_parameter": {}, "source_time": 1714777729.312107, "agent_name": "Micha\u0142 Szczepanik", "agent_email": "m.szczepanik@fz-juelich.de"}]}, "path": "input/MRI/processed/sub-61/ses-2/func/SB61_1_2_20171113_093821SmoothBet_mask.nii.gz", "contentbytesize": 2131, "name": "SB61_1_2_20171113_093821SmoothBet_mask.nii.gz"}, {"type": "file", "dataset_id": "83b73949-b6c3-4b2b-81b2-cc3f7236a048", "dataset_version": "eb38ea8ece37da4ee1b2037aec3c894dc7e9e145", "metadata_sources": {"key_source_map": {}, "sources": [{"source_name": "manual_addition", "source_version": "0.1.0", "source_parameter": {}, "source_time": 1714777729.312107, "agent_name": "Micha\u0142 Szczepanik", "agent_email": "m.szczepanik@fz-juelich.de"}]}, "path": "input/MRI/processed/sub-61/ses-2/func/SB61_1_2_20171113_093821SmoothBettransMatrixAff.txt", "contentbytesize": 135, "name": "SB61_1_2_20171113_093821SmoothBettransMatrixAff.txt"}, {"type": "file", "dataset_id": "83b73949-b6c3-4b2b-81b2-cc3f7236a048", "dataset_version": "eb38ea8ece37da4ee1b2037aec3c894dc7e9e145", "metadata_sources": {"key_source_map": {}, "sources": [{"source_name": "manual_addition", "source_version": "0.1.0", "source_parameter": {}, "source_time": 1714777729.312107, "agent_name": "Micha\u0142 Szczepanik", "agent_email": "m.szczepanik@fz-juelich.de"}]}, "path": "input/MRI/processed/sub-61/ses-2/func/Seed_ROIs.nii.gz", "contentbytesize": 525838, "name": "Seed_ROIs.nii.gz"}, {"type": "file", "dataset_id": "83b73949-b6c3-4b2b-81b2-cc3f7236a048", "dataset_version": "eb38ea8ece37da4ee1b2037aec3c894dc7e9e145", "metadata_sources": {"key_source_map": {}, "sources": [{"source_name": "manual_addition", "source_version": "0.1.0", "source_parameter": {}, "source_time": 1714777729.312107, "agent_name": "Micha\u0142 Szczepanik", "agent_email": "m.szczepanik@fz-juelich.de"}]}, "path": "input/MRI/processed/sub-61/ses-2/func/preprocess.log", "contentbytesize": 126, "name": "preprocess.log"}, {"type": "file", "dataset_id": "83b73949-b6c3-4b2b-81b2-cc3f7236a048", "dataset_version": "eb38ea8ece37da4ee1b2037aec3c894dc7e9e145", "metadata_sources": {"key_source_map": {}, "sources": [{"source_name": "manual_addition", "source_version": "0.1.0", "source_parameter": {}, "source_time": 1714777729.312107, "agent_name": "Micha\u0142 Szczepanik", "agent_email": "m.szczepanik@fz-juelich.de"}]}, "path": "input/MRI/processed/sub-61/ses-2/func/process.log", "contentbytesize": 8779, "name": "process.log"}, {"type": "directory", "name": "rawMonData", "path": "input/MRI/processed/sub-61/ses-2/func/rawMonData", "dataset_id": "83b73949-b6c3-4b2b-81b2-cc3f7236a048", "dataset_version": "eb38ea8ece37da4ee1b2037aec3c894dc7e9e145"}, {"type": "file", "dataset_id": "83b73949-b6c3-4b2b-81b2-cc3f7236a048", "dataset_version": "eb38ea8ece37da4ee1b2037aec3c894dc7e9e145", "metadata_sources": {"key_source_map": {}, "sources": [{"source_name": "manual_addition", "source_version": "0.1.0", "source_parameter": {}, "source_time": 1714777729.312107, "agent_name": "Micha\u0142 Szczepanik", "agent_email": "m.szczepanik@fz-juelich.de"}]}, "path": "input/MRI/processed/sub-61/ses-2/func/reg.log", "contentbytesize": 0, "name": "reg.log"}, {"type": "file", "dataset_id": "83b73949-b6c3-4b2b-81b2-cc3f7236a048", "dataset_version": "eb38ea8ece37da4ee1b2037aec3c894dc7e9e145", "metadata_sources": {"key_source_map": {}, "sources": [{"source_name": "manual_addition", "source_version": "0.1.0", "source_parameter": {}, "source_time": 1714777729.312107, "agent_name": "Micha\u0142 Szczepanik", "agent_email": "m.szczepanik@fz-juelich.de"}]}, "path": "input/MRI/processed/sub-61/ses-2/func/registration.log", "contentbytesize": 230, "name": "registration.log"}, {"type": "directory", "name": "regr", "path": "input/MRI/processed/sub-61/ses-2/func/regr", "dataset_id": "83b73949-b6c3-4b2b-81b2-cc3f7236a048", "dataset_version": "eb38ea8ece37da4ee1b2037aec3c894dc7e9e145"}, {"type": "directory", "name": "results", "path": "input/MRI/processed/sub-61/ses-2/func/results", "dataset_id": "83b73949-b6c3-4b2b-81b2-cc3f7236a048", "dataset_version": "eb38ea8ece37da4ee1b2037aec3c894dc7e9e145"}, {"type": "directory", "name": "rs-fMRI_mcf", "path": "input/MRI/processed/sub-61/ses-2/func/rs-fMRI_mcf", "dataset_id": "83b73949-b6c3-4b2b-81b2-cc3f7236a048", "dataset_version": "eb38ea8ece37da4ee1b2037aec3c894dc7e9e145"}, {"type": "directory", "name": "rs-fMRI_niiData", "path": "input/MRI/processed/sub-61/ses-2/func/rs-fMRI_niiData", "dataset_id": "83b73949-b6c3-4b2b-81b2-cc3f7236a048", "dataset_version": "eb38ea8ece37da4ee1b2037aec3c894dc7e9e145"}, {"type": "directory", "name": "txtRegrPython", "path": "input/MRI/processed/sub-61/ses-2/func/txtRegrPython", "dataset_id": "83b73949-b6c3-4b2b-81b2-cc3f7236a048", "dataset_version": "eb38ea8ece37da4ee1b2037aec3c894dc7e9e145"}], "path": "input/MRI/processed/sub-61/ses-2/func", "name": "func"}