{"type": "directory", "dataset_id": "021bcaca-5a60-5f56-b712-d9f57859b4fa", "dataset_version": "latest", "children": [{"type": "file", "dataset_id": "021bcaca-5a60-5f56-b712-d9f57859b4fa", "dataset_version": "latest", "metadata_sources": {"key_source_map": {}, "sources": [{"source_name": "tabby", "source_version": "0.1.0", "source_parameter": {}, "source_time": 1710539295.012829, "agent_name": "Micha\u0142 Szczepanik", "agent_email": "m.szczepanik@fz-juelich.de"}]}, "path": "6244/func/wm_task/stand/PA/6244_fep2d_bold_task_PA_20220826083522_19.json", "contentbytesize": 2301, "name": "6244_fep2d_bold_task_PA_20220826083522_19.json"}, {"type": "file", "dataset_id": "021bcaca-5a60-5f56-b712-d9f57859b4fa", "dataset_version": "latest", "metadata_sources": {"key_source_map": {}, "sources": [{"source_name": "tabby", "source_version": "0.1.0", "source_parameter": {}, "source_time": 1710539295.012829, "agent_name": "Micha\u0142 Szczepanik", "agent_email": "m.szczepanik@fz-juelich.de"}]}, "path": "6244/func/wm_task/stand/PA/6244_fep2d_bold_task_PA_20220826083522_19.nii", "contentbytesize": 2262368, "name": "6244_fep2d_bold_task_PA_20220826083522_19.nii"}], "path": "6244/func/wm_task/stand/PA", "name": "PA"}