{"type": "directory", "dataset_id": "f1a7ead6-a448-4c29-aad5-921e59db6aba", "dataset_version": "9461caf6458e09fa69879438f6984b1d9ad4ffe9", "children": [{"type": "file", "dataset_id": "f1a7ead6-a448-4c29-aad5-921e59db6aba", "dataset_version": "9461caf6458e09fa69879438f6984b1d9ad4ffe9", "metadata_sources": {"key_source_map": {}, "sources": [{"source_name": "metalad_core", "source_version": "1", "source_parameter": {}, "source_time": 1681820212.8038275, "agent_email": "m.szczepanik@fz-juelich.de", "agent_name": "Micha\u0142 Szczepanik"}]}, "path": "MRI_raw_data/Treatment/P7/physio/GV_T3_15_4_1_2_20190924_104243/GV_T3_15_4_1_2_20190924_104243.PHYSWAV.1.I32", "contentbytesize": 352256, "name": "GV_T3_15_4_1_2_20190924_104243.PHYSWAV.1.I32"}, {"type": "file", "dataset_id": "f1a7ead6-a448-4c29-aad5-921e59db6aba", "dataset_version": "9461caf6458e09fa69879438f6984b1d9ad4ffe9", "metadata_sources": {"key_source_map": {}, "sources": [{"source_name": "metalad_core", "source_version": "1", "source_parameter": {}, "source_time": 1681820212.8046718, "agent_email": "m.szczepanik@fz-juelich.de", "agent_name": "Micha\u0142 Szczepanik"}]}, "path": "MRI_raw_data/Treatment/P7/physio/GV_T3_15_4_1_2_20190924_104243/GV_T3_15_4_1_2_20190924_104243.PHYSWAV.2.I32", "contentbytesize": 1536000, "name": "GV_T3_15_4_1_2_20190924_104243.PHYSWAV.2.I32"}, {"type": "file", "dataset_id": "f1a7ead6-a448-4c29-aad5-921e59db6aba", "dataset_version": "9461caf6458e09fa69879438f6984b1d9ad4ffe9", "metadata_sources": {"key_source_map": {}, "sources": [{"source_name": "metalad_core", "source_version": "1", "source_parameter": {}, "source_time": 1681820212.8078578, "agent_email": "m.szczepanik@fz-juelich.de", "agent_name": "Micha\u0142 Szczepanik"}]}, "path": "MRI_raw_data/Treatment/P7/physio/GV_T3_15_4_1_2_20190924_104243/GV_T3_15_4_1_2_20190924_104243.10S.ASC", "contentbytesize": 13621, "name": "GV_T3_15_4_1_2_20190924_104243.10S.ASC"}, {"type": "file", "dataset_id": "f1a7ead6-a448-4c29-aad5-921e59db6aba", "dataset_version": "9461caf6458e09fa69879438f6984b1d9ad4ffe9", "metadata_sources": {"key_source_map": {}, "sources": [{"source_name": "metalad_core", "source_version": "1", "source_parameter": {}, "source_time": 1681820212.8140962, "agent_email": "m.szczepanik@fz-juelich.de", "agent_name": "Micha\u0142 Szczepanik"}]}, "path": "MRI_raw_data/Treatment/P7/physio/GV_T3_15_4_1_2_20190924_104243/GV_T3_15_4_1_2_20190924_104243.PHYSWAV.4.I32", "contentbytesize": 286720, "name": "GV_T3_15_4_1_2_20190924_104243.PHYSWAV.4.I32"}, {"type": "file", "dataset_id": "f1a7ead6-a448-4c29-aad5-921e59db6aba", "dataset_version": "9461caf6458e09fa69879438f6984b1d9ad4ffe9", "metadata_sources": {"key_source_map": {}, "sources": [{"source_name": "metalad_core", "source_version": "1", "source_parameter": {}, "source_time": 1681820212.8125238, "agent_email": "m.szczepanik@fz-juelich.de", "agent_name": "Micha\u0142 Szczepanik"}]}, "path": "MRI_raw_data/Treatment/P7/physio/GV_T3_15_4_1_2_20190924_104243/GV_T3_15_4_1_2_20190924_104243.PHYSWAV.6.I32", "contentbytesize": 2512896, "name": "GV_T3_15_4_1_2_20190924_104243.PHYSWAV.6.I32"}, {"type": "file", "dataset_id": "f1a7ead6-a448-4c29-aad5-921e59db6aba", "dataset_version": "9461caf6458e09fa69879438f6984b1d9ad4ffe9", "metadata_sources": {"key_source_map": {}, "sources": [{"source_name": "metalad_core", "source_version": "1", "source_parameter": {}, "source_time": 1681820212.8126502, "agent_email": "m.szczepanik@fz-juelich.de", "agent_name": "Micha\u0142 Szczepanik"}]}, "path": "MRI_raw_data/Treatment/P7/physio/GV_T3_15_4_1_2_20190924_104243/GV_T3_15_4_1_2_20190924_104243.PHYSWAV.5.I32", "contentbytesize": 5744640, "name": "GV_T3_15_4_1_2_20190924_104243.PHYSWAV.5.I32"}, {"type": "file", "dataset_id": "f1a7ead6-a448-4c29-aad5-921e59db6aba", "dataset_version": "9461caf6458e09fa69879438f6984b1d9ad4ffe9", "metadata_sources": {"key_source_map": {}, "sources": [{"source_name": "metalad_core", "source_version": "1", "source_parameter": {}, "source_time": 1681820212.8210773, "agent_email": "m.szczepanik@fz-juelich.de", "agent_name": "Micha\u0142 Szczepanik"}]}, "path": "MRI_raw_data/Treatment/P7/physio/GV_T3_15_4_1_2_20190924_104243/GV_T3_15_4_1_2_20190924_104243.SCR.WMF", "contentbytesize": 99700, "name": "GV_T3_15_4_1_2_20190924_104243.SCR.WMF"}, {"type": "file", "dataset_id": "f1a7ead6-a448-4c29-aad5-921e59db6aba", "dataset_version": "9461caf6458e09fa69879438f6984b1d9ad4ffe9", "metadata_sources": {"key_source_map": {}, "sources": [{"source_name": "metalad_core", "source_version": "1", "source_parameter": {}, "source_time": 1681820212.822145, "agent_email": "m.szczepanik@fz-juelich.de", "agent_name": "Micha\u0142 Szczepanik"}]}, "path": "MRI_raw_data/Treatment/P7/physio/GV_T3_15_4_1_2_20190924_104243/GV_T3_15_4_1_2_20190924_104243.PHYSWAV.6.ASC", "contentbytesize": 95304, "name": "GV_T3_15_4_1_2_20190924_104243.PHYSWAV.6.ASC"}, {"type": "file", "dataset_id": "f1a7ead6-a448-4c29-aad5-921e59db6aba", "dataset_version": "9461caf6458e09fa69879438f6984b1d9ad4ffe9", "metadata_sources": {"key_source_map": {}, "sources": [{"source_name": "metalad_core", "source_version": "1", "source_parameter": {}, "source_time": 1681820212.8282428, "agent_email": "m.szczepanik@fz-juelich.de", "agent_name": "Micha\u0142 Szczepanik"}]}, "path": "MRI_raw_data/Treatment/P7/physio/GV_T3_15_4_1_2_20190924_104243/GV_T3_15_4_1_2_20190924_104243.PHYSWAV.7.I32", "contentbytesize": 13824000, "name": "GV_T3_15_4_1_2_20190924_104243.PHYSWAV.7.I32"}, {"type": "file", "dataset_id": "f1a7ead6-a448-4c29-aad5-921e59db6aba", "dataset_version": "9461caf6458e09fa69879438f6984b1d9ad4ffe9", "metadata_sources": {"key_source_map": {}, "sources": [{"source_name": "metalad_core", "source_version": "1", "source_parameter": {}, "source_time": 1681820212.8275635, "agent_email": "m.szczepanik@fz-juelich.de", "agent_name": "Micha\u0142 Szczepanik"}]}, "path": "MRI_raw_data/Treatment/P7/physio/GV_T3_15_4_1_2_20190924_104243/GV_T3_15_4_1_2_20190924_104243.PRO.TXT", "contentbytesize": 176, "name": "GV_T3_15_4_1_2_20190924_104243.PRO.TXT"}, {"type": "file", "dataset_id": "f1a7ead6-a448-4c29-aad5-921e59db6aba", "dataset_version": "9461caf6458e09fa69879438f6984b1d9ad4ffe9", "metadata_sources": {"key_source_map": {}, "sources": [{"source_name": "metalad_core", "source_version": "1", "source_parameter": {}, "source_time": 1681820212.8433201, "agent_email": "m.szczepanik@fz-juelich.de", "agent_name": "Micha\u0142 Szczepanik"}]}, "path": "MRI_raw_data/Treatment/P7/physio/GV_T3_15_4_1_2_20190924_104243/GV_T3_15_4_1_2_20190924_104243.SCR.JPG", "contentbytesize": 354486, "name": "GV_T3_15_4_1_2_20190924_104243.SCR.JPG"}], "path": "MRI_raw_data/Treatment/P7/physio/GV_T3_15_4_1_2_20190924_104243", "name": "GV_T3_15_4_1_2_20190924_104243"}