{"type": "directory", "dataset_id": "f1a7ead6-a448-4c29-aad5-921e59db6aba", "dataset_version": "9461caf6458e09fa69879438f6984b1d9ad4ffe9", "children": [{"type": "file", "dataset_id": "f1a7ead6-a448-4c29-aad5-921e59db6aba", "dataset_version": "9461caf6458e09fa69879438f6984b1d9ad4ffe9", "metadata_sources": {"key_source_map": {}, "sources": [{"source_name": "metalad_core", "source_version": "1", "source_parameter": {}, "source_time": 1681820208.356799, "agent_email": "m.szczepanik@fz-juelich.de", "agent_name": "Micha\u0142 Szczepanik"}]}, "path": "MRI_raw_data/Treatment/P7/GV_T3_12_2_1_3_20190820_104019/10/acqp", "contentbytesize": 21822, "name": "acqp"}, {"type": "file", "dataset_id": "f1a7ead6-a448-4c29-aad5-921e59db6aba", "dataset_version": "9461caf6458e09fa69879438f6984b1d9ad4ffe9", "metadata_sources": {"key_source_map": {}, "sources": [{"source_name": "metalad_core", "source_version": "1", "source_parameter": {}, "source_time": 1681820208.3519065, "agent_email": "m.szczepanik@fz-juelich.de", "agent_name": "Micha\u0142 Szczepanik"}]}, "path": "MRI_raw_data/Treatment/P7/GV_T3_12_2_1_3_20190820_104019/10/AdjStatePerScan", "contentbytesize": 893, "name": "AdjStatePerScan"}, {"type": "directory", "name": "pdata", "path": "MRI_raw_data/Treatment/P7/GV_T3_12_2_1_3_20190820_104019/10/pdata", "dataset_id": "f1a7ead6-a448-4c29-aad5-921e59db6aba", "dataset_version": "9461caf6458e09fa69879438f6984b1d9ad4ffe9"}, {"type": "file", "dataset_id": "f1a7ead6-a448-4c29-aad5-921e59db6aba", "dataset_version": "9461caf6458e09fa69879438f6984b1d9ad4ffe9", "metadata_sources": {"key_source_map": {}, "sources": [{"source_name": "metalad_core", "source_version": "1", "source_parameter": {}, "source_time": 1681820208.361044, "agent_email": "m.szczepanik@fz-juelich.de", "agent_name": "Micha\u0142 Szczepanik"}]}, "path": "MRI_raw_data/Treatment/P7/GV_T3_12_2_1_3_20190820_104019/10/fid", "contentbytesize": 189420000, "name": "fid"}, {"type": "file", "dataset_id": "f1a7ead6-a448-4c29-aad5-921e59db6aba", "dataset_version": "9461caf6458e09fa69879438f6984b1d9ad4ffe9", "metadata_sources": {"key_source_map": {}, "sources": [{"source_name": "metalad_core", "source_version": "1", "source_parameter": {}, "source_time": 1681820208.3567982, "agent_email": "m.szczepanik@fz-juelich.de", "agent_name": "Micha\u0142 Szczepanik"}]}, "path": "MRI_raw_data/Treatment/P7/GV_T3_12_2_1_3_20190820_104019/10/configscan", "contentbytesize": 7063, "name": "configscan"}, {"type": "file", "dataset_id": "f1a7ead6-a448-4c29-aad5-921e59db6aba", "dataset_version": "9461caf6458e09fa69879438f6984b1d9ad4ffe9", "metadata_sources": {"key_source_map": {}, "sources": [{"source_name": "metalad_core", "source_version": "1", "source_parameter": {}, "source_time": 1681820208.3645208, "agent_email": "m.szczepanik@fz-juelich.de", "agent_name": "Micha\u0142 Szczepanik"}]}, "path": "MRI_raw_data/Treatment/P7/GV_T3_12_2_1_3_20190820_104019/10/method", "contentbytesize": 44685, "name": "method"}, {"type": "file", "dataset_id": "f1a7ead6-a448-4c29-aad5-921e59db6aba", "dataset_version": "9461caf6458e09fa69879438f6984b1d9ad4ffe9", "metadata_sources": {"key_source_map": {}, "sources": [{"source_name": "metalad_core", "source_version": "1", "source_parameter": {}, "source_time": 1681820208.467734, "agent_email": "m.szczepanik@fz-juelich.de", "agent_name": "Micha\u0142 Szczepanik"}]}, "path": "MRI_raw_data/Treatment/P7/GV_T3_12_2_1_3_20190820_104019/10/pulseprogram", "contentbytesize": 39124, "name": "pulseprogram"}, {"type": "file", "dataset_id": "f1a7ead6-a448-4c29-aad5-921e59db6aba", "dataset_version": "9461caf6458e09fa69879438f6984b1d9ad4ffe9", "metadata_sources": {"key_source_map": {}, "sources": [{"source_name": "metalad_core", "source_version": "1", "source_parameter": {}, "source_time": 1681820208.4797993, "agent_email": "m.szczepanik@fz-juelich.de", "agent_name": "Micha\u0142 Szczepanik"}]}, "path": "MRI_raw_data/Treatment/P7/GV_T3_12_2_1_3_20190820_104019/10/uxnmr.info", "contentbytesize": 7437, "name": "uxnmr.info"}, {"type": "file", "dataset_id": "f1a7ead6-a448-4c29-aad5-921e59db6aba", "dataset_version": "9461caf6458e09fa69879438f6984b1d9ad4ffe9", "metadata_sources": {"key_source_map": {}, "sources": [{"source_name": "metalad_core", "source_version": "1", "source_parameter": {}, "source_time": 1681820208.4827518, "agent_email": "m.szczepanik@fz-juelich.de", "agent_name": "Micha\u0142 Szczepanik"}]}, "path": "MRI_raw_data/Treatment/P7/GV_T3_12_2_1_3_20190820_104019/10/visu_pars", "contentbytesize": 133546, "name": "visu_pars"}, {"type": "file", "dataset_id": "f1a7ead6-a448-4c29-aad5-921e59db6aba", "dataset_version": "9461caf6458e09fa69879438f6984b1d9ad4ffe9", "metadata_sources": {"key_source_map": {}, "sources": [{"source_name": "metalad_core", "source_version": "1", "source_parameter": {}, "source_time": 1681820208.4687948, "agent_email": "m.szczepanik@fz-juelich.de", "agent_name": "Micha\u0142 Szczepanik"}]}, "path": "MRI_raw_data/Treatment/P7/GV_T3_12_2_1_3_20190820_104019/10/spnam41", "contentbytesize": 29212, "name": "spnam41"}, {"type": "file", "dataset_id": "f1a7ead6-a448-4c29-aad5-921e59db6aba", "dataset_version": "9461caf6458e09fa69879438f6984b1d9ad4ffe9", "metadata_sources": {"key_source_map": {}, "sources": [{"source_name": "metalad_core", "source_version": "1", "source_parameter": {}, "source_time": 1681820208.488051, "agent_email": "m.szczepanik@fz-juelich.de", "agent_name": "Micha\u0142 Szczepanik"}]}, "path": "MRI_raw_data/Treatment/P7/GV_T3_12_2_1_3_20190820_104019/10/uxnmr.par", "contentbytesize": 26513, "name": "uxnmr.par"}, {"type": "file", "dataset_id": "f1a7ead6-a448-4c29-aad5-921e59db6aba", "dataset_version": "9461caf6458e09fa69879438f6984b1d9ad4ffe9", "metadata_sources": {"key_source_map": {}, "sources": [{"source_name": "metalad_core", "source_version": "1", "source_parameter": {}, "source_time": 1681820208.4662895, "agent_email": "m.szczepanik@fz-juelich.de", "agent_name": "Micha\u0142 Szczepanik"}]}, "path": "MRI_raw_data/Treatment/P7/GV_T3_12_2_1_3_20190820_104019/10/specpar", "contentbytesize": 937, "name": "specpar"}], "path": "MRI_raw_data/Treatment/P7/GV_T3_12_2_1_3_20190820_104019/10", "name": "10"}