{"type": "directory", "dataset_id": "945795a4-f4d0-43dc-b51a-e73a79ae8d47", "dataset_version": "7e8814fb39bfb7e6c72340c7c516f46896a2f529", "children": [{"type": "file", "dataset_id": "945795a4-f4d0-43dc-b51a-e73a79ae8d47", "dataset_version": "7e8814fb39bfb7e6c72340c7c516f46896a2f529", "metadata_sources": {"key_source_map": {}, "sources": [{"source_name": "metalad_core", "source_version": "1", "source_parameter": {}, "source_time": 1681821377.318084, "agent_email": "m.szczepanik@fz-juelich.de", "agent_name": "Micha\u0142 Szczepanik"}]}, "path": "inputs/mri/raw_data/P7/SP_T1_23_2_1_3_20180618_124828/3/AdjStatePerScan", "contentbytesize": 733, "name": "AdjStatePerScan"}, {"type": "file", "dataset_id": "945795a4-f4d0-43dc-b51a-e73a79ae8d47", "dataset_version": "7e8814fb39bfb7e6c72340c7c516f46896a2f529", "metadata_sources": {"key_source_map": {}, "sources": [{"source_name": "metalad_core", "source_version": "1", "source_parameter": {}, "source_time": 1681821377.3172333, "agent_email": "m.szczepanik@fz-juelich.de", "agent_name": "Micha\u0142 Szczepanik"}]}, "path": "inputs/mri/raw_data/P7/SP_T1_23_2_1_3_20180618_124828/3/acqp", "contentbytesize": 16105, "name": "acqp"}, {"type": "file", "dataset_id": "945795a4-f4d0-43dc-b51a-e73a79ae8d47", "dataset_version": "7e8814fb39bfb7e6c72340c7c516f46896a2f529", "metadata_sources": {"key_source_map": {}, "sources": [{"source_name": "metalad_core", "source_version": "1", "source_parameter": {}, "source_time": 1681821377.3197365, "agent_email": "m.szczepanik@fz-juelich.de", "agent_name": "Micha\u0142 Szczepanik"}]}, "path": "inputs/mri/raw_data/P7/SP_T1_23_2_1_3_20180618_124828/3/fid", "contentbytesize": 16384, "name": "fid"}, {"type": "file", "dataset_id": "945795a4-f4d0-43dc-b51a-e73a79ae8d47", "dataset_version": "7e8814fb39bfb7e6c72340c7c516f46896a2f529", "metadata_sources": {"key_source_map": {}, "sources": [{"source_name": "metalad_core", "source_version": "1", "source_parameter": {}, "source_time": 1681821377.3180377, "agent_email": "m.szczepanik@fz-juelich.de", "agent_name": "Micha\u0142 Szczepanik"}]}, "path": "inputs/mri/raw_data/P7/SP_T1_23_2_1_3_20180618_124828/3/configscan", "contentbytesize": 6888, "name": "configscan"}, {"type": "file", "dataset_id": "945795a4-f4d0-43dc-b51a-e73a79ae8d47", "dataset_version": "7e8814fb39bfb7e6c72340c7c516f46896a2f529", "metadata_sources": {"key_source_map": {}, "sources": [{"source_name": "metalad_core", "source_version": "1", "source_parameter": {}, "source_time": 1681821377.3221765, "agent_email": "m.szczepanik@fz-juelich.de", "agent_name": "Micha\u0142 Szczepanik"}]}, "path": "inputs/mri/raw_data/P7/SP_T1_23_2_1_3_20180618_124828/3/method", "contentbytesize": 83791, "name": "method"}, {"type": "directory", "name": "pdata", "path": "inputs/mri/raw_data/P7/SP_T1_23_2_1_3_20180618_124828/3/pdata", "dataset_id": "945795a4-f4d0-43dc-b51a-e73a79ae8d47", "dataset_version": "7e8814fb39bfb7e6c72340c7c516f46896a2f529"}, {"type": "file", "dataset_id": "945795a4-f4d0-43dc-b51a-e73a79ae8d47", "dataset_version": "7e8814fb39bfb7e6c72340c7c516f46896a2f529", "metadata_sources": {"key_source_map": {}, "sources": [{"source_name": "metalad_core", "source_version": "1", "source_parameter": {}, "source_time": 1681821377.3544173, "agent_email": "m.szczepanik@fz-juelich.de", "agent_name": "Micha\u0142 Szczepanik"}]}, "path": "inputs/mri/raw_data/P7/SP_T1_23_2_1_3_20180618_124828/3/specpar", "contentbytesize": 898, "name": "specpar"}, {"type": "file", "dataset_id": "945795a4-f4d0-43dc-b51a-e73a79ae8d47", "dataset_version": "7e8814fb39bfb7e6c72340c7c516f46896a2f529", "metadata_sources": {"key_source_map": {}, "sources": [{"source_name": "metalad_core", "source_version": "1", "source_parameter": {}, "source_time": 1681821377.353085, "agent_email": "m.szczepanik@fz-juelich.de", "agent_name": "Micha\u0142 Szczepanik"}]}, "path": "inputs/mri/raw_data/P7/SP_T1_23_2_1_3_20180618_124828/3/rawdata.job0", "contentbytesize": 32768, "name": "rawdata.job0"}, {"type": "file", "dataset_id": "945795a4-f4d0-43dc-b51a-e73a79ae8d47", "dataset_version": "7e8814fb39bfb7e6c72340c7c516f46896a2f529", "metadata_sources": {"key_source_map": {}, "sources": [{"source_name": "metalad_core", "source_version": "1", "source_parameter": {}, "source_time": 1681821377.3568182, "agent_email": "m.szczepanik@fz-juelich.de", "agent_name": "Micha\u0142 Szczepanik"}]}, "path": "inputs/mri/raw_data/P7/SP_T1_23_2_1_3_20180618_124828/3/spnam1", "contentbytesize": 7410, "name": "spnam1"}, {"type": "file", "dataset_id": "945795a4-f4d0-43dc-b51a-e73a79ae8d47", "dataset_version": "7e8814fb39bfb7e6c72340c7c516f46896a2f529", "metadata_sources": {"key_source_map": {}, "sources": [{"source_name": "metalad_core", "source_version": "1", "source_parameter": {}, "source_time": 1681821377.3527093, "agent_email": "m.szczepanik@fz-juelich.de", "agent_name": "Micha\u0142 Szczepanik"}]}, "path": "inputs/mri/raw_data/P7/SP_T1_23_2_1_3_20180618_124828/3/pulseprogram", "contentbytesize": 39746, "name": "pulseprogram"}, {"type": "file", "dataset_id": "945795a4-f4d0-43dc-b51a-e73a79ae8d47", "dataset_version": "7e8814fb39bfb7e6c72340c7c516f46896a2f529", "metadata_sources": {"key_source_map": {}, "sources": [{"source_name": "metalad_core", "source_version": "1", "source_parameter": {}, "source_time": 1681821377.350486, "agent_email": "m.szczepanik@fz-juelich.de", "agent_name": "Micha\u0142 Szczepanik"}]}, "path": "inputs/mri/raw_data/P7/SP_T1_23_2_1_3_20180618_124828/3/spectrum.dat", "contentbytesize": 65536, "name": "spectrum.dat"}, {"type": "file", "dataset_id": "945795a4-f4d0-43dc-b51a-e73a79ae8d47", "dataset_version": "7e8814fb39bfb7e6c72340c7c516f46896a2f529", "metadata_sources": {"key_source_map": {}, "sources": [{"source_name": "metalad_core", "source_version": "1", "source_parameter": {}, "source_time": 1681821377.361515, "agent_email": "m.szczepanik@fz-juelich.de", "agent_name": "Micha\u0142 Szczepanik"}]}, "path": "inputs/mri/raw_data/P7/SP_T1_23_2_1_3_20180618_124828/3/uxnmr.info", "contentbytesize": 7266, "name": "uxnmr.info"}, {"type": "file", "dataset_id": "945795a4-f4d0-43dc-b51a-e73a79ae8d47", "dataset_version": "7e8814fb39bfb7e6c72340c7c516f46896a2f529", "metadata_sources": {"key_source_map": {}, "sources": [{"source_name": "metalad_core", "source_version": "1", "source_parameter": {}, "source_time": 1681821377.3672452, "agent_email": "m.szczepanik@fz-juelich.de", "agent_name": "Micha\u0142 Szczepanik"}]}, "path": "inputs/mri/raw_data/P7/SP_T1_23_2_1_3_20180618_124828/3/uxnmr.par", "contentbytesize": 25727, "name": "uxnmr.par"}, {"type": "file", "dataset_id": "945795a4-f4d0-43dc-b51a-e73a79ae8d47", "dataset_version": "7e8814fb39bfb7e6c72340c7c516f46896a2f529", "metadata_sources": {"key_source_map": {}, "sources": [{"source_name": "metalad_core", "source_version": "1", "source_parameter": {}, "source_time": 1681821377.3665814, "agent_email": "m.szczepanik@fz-juelich.de", "agent_name": "Micha\u0142 Szczepanik"}]}, "path": "inputs/mri/raw_data/P7/SP_T1_23_2_1_3_20180618_124828/3/visu_pars", "contentbytesize": 3029, "name": "visu_pars"}], "path": "inputs/mri/raw_data/P7/SP_T1_23_2_1_3_20180618_124828/3", "name": "3"}