{"type": "directory", "dataset_id": "f1a7ead6-a448-4c29-aad5-921e59db6aba", "dataset_version": "9461caf6458e09fa69879438f6984b1d9ad4ffe9", "children": [{"type": "file", "dataset_id": "f1a7ead6-a448-4c29-aad5-921e59db6aba", "dataset_version": "9461caf6458e09fa69879438f6984b1d9ad4ffe9", "metadata_sources": {"key_source_map": {}, "sources": [{"source_name": "metalad_core", "source_version": "1", "source_parameter": {}, "source_time": 1681820207.471362, "agent_email": "m.szczepanik@fz-juelich.de", "agent_name": "Micha\u0142 Szczepanik"}]}, "path": "MRI_raw_data/Treatment/P56/physio/GV_T3_12_1_1_8_20191008_102322/GV_T3_12_1_1_8_20191008_102322.10S.ASC", "contentbytesize": 20923, "name": "GV_T3_12_1_1_8_20191008_102322.10S.ASC"}, {"type": "file", "dataset_id": "f1a7ead6-a448-4c29-aad5-921e59db6aba", "dataset_version": "9461caf6458e09fa69879438f6984b1d9ad4ffe9", "metadata_sources": {"key_source_map": {}, "sources": [{"source_name": "metalad_core", "source_version": "1", "source_parameter": {}, "source_time": 1681820207.478696, "agent_email": "m.szczepanik@fz-juelich.de", "agent_name": "Micha\u0142 Szczepanik"}]}, "path": "MRI_raw_data/Treatment/P56/physio/GV_T3_12_1_1_8_20191008_102322/GV_T3_12_1_1_8_20191008_102322.PHYSWAV..I32", "contentbytesize": 5791744, "name": "GV_T3_12_1_1_8_20191008_102322.PHYSWAV..I32"}, {"type": "file", "dataset_id": "f1a7ead6-a448-4c29-aad5-921e59db6aba", "dataset_version": "9461caf6458e09fa69879438f6984b1d9ad4ffe9", "metadata_sources": {"key_source_map": {}, "sources": [{"source_name": "metalad_core", "source_version": "1", "source_parameter": {}, "source_time": 1681820207.475655, "agent_email": "m.szczepanik@fz-juelich.de", "agent_name": "Micha\u0142 Szczepanik"}]}, "path": "MRI_raw_data/Treatment/P56/physio/GV_T3_12_1_1_8_20191008_102322/GV_T3_12_1_1_8_20191008_102322.PHYSWAV.1.I32", "contentbytesize": 335872, "name": "GV_T3_12_1_1_8_20191008_102322.PHYSWAV.1.I32"}, {"type": "file", "dataset_id": "f1a7ead6-a448-4c29-aad5-921e59db6aba", "dataset_version": "9461caf6458e09fa69879438f6984b1d9ad4ffe9", "metadata_sources": {"key_source_map": {}, "sources": [{"source_name": "metalad_core", "source_version": "1", "source_parameter": {}, "source_time": 1681820207.4841087, "agent_email": "m.szczepanik@fz-juelich.de", "agent_name": "Micha\u0142 Szczepanik"}]}, "path": "MRI_raw_data/Treatment/P56/physio/GV_T3_12_1_1_8_20191008_102322/GV_T3_12_1_1_8_20191008_102322.PHYSWAV.10.ASC", "contentbytesize": 95818, "name": "GV_T3_12_1_1_8_20191008_102322.PHYSWAV.10.ASC"}, {"type": "file", "dataset_id": "f1a7ead6-a448-4c29-aad5-921e59db6aba", "dataset_version": "9461caf6458e09fa69879438f6984b1d9ad4ffe9", "metadata_sources": {"key_source_map": {}, "sources": [{"source_name": "metalad_core", "source_version": "1", "source_parameter": {}, "source_time": 1681820207.479313, "agent_email": "m.szczepanik@fz-juelich.de", "agent_name": "Micha\u0142 Szczepanik"}]}, "path": "MRI_raw_data/Treatment/P56/physio/GV_T3_12_1_1_8_20191008_102322/GV_T3_12_1_1_8_20191008_102322.PHYSWAV.10.I32", "contentbytesize": 2510848, "name": "GV_T3_12_1_1_8_20191008_102322.PHYSWAV.10.I32"}, {"type": "file", "dataset_id": "f1a7ead6-a448-4c29-aad5-921e59db6aba", "dataset_version": "9461caf6458e09fa69879438f6984b1d9ad4ffe9", "metadata_sources": {"key_source_map": {}, "sources": [{"source_name": "metalad_core", "source_version": "1", "source_parameter": {}, "source_time": 1681820207.4810448, "agent_email": "m.szczepanik@fz-juelich.de", "agent_name": "Micha\u0142 Szczepanik"}]}, "path": "MRI_raw_data/Treatment/P56/physio/GV_T3_12_1_1_8_20191008_102322/GV_T3_12_1_1_8_20191008_102322.PHYSWAV.3.I32", "contentbytesize": 14336, "name": "GV_T3_12_1_1_8_20191008_102322.PHYSWAV.3.I32"}, {"type": "file", "dataset_id": "f1a7ead6-a448-4c29-aad5-921e59db6aba", "dataset_version": "9461caf6458e09fa69879438f6984b1d9ad4ffe9", "metadata_sources": {"key_source_map": {}, "sources": [{"source_name": "metalad_core", "source_version": "1", "source_parameter": {}, "source_time": 1681820207.4821334, "agent_email": "m.szczepanik@fz-juelich.de", "agent_name": "Micha\u0142 Szczepanik"}]}, "path": "MRI_raw_data/Treatment/P56/physio/GV_T3_12_1_1_8_20191008_102322/GV_T3_12_1_1_8_20191008_102322.PHYSWAV.5.I32", "contentbytesize": 305152, "name": "GV_T3_12_1_1_8_20191008_102322.PHYSWAV.5.I32"}, {"type": "file", "dataset_id": "f1a7ead6-a448-4c29-aad5-921e59db6aba", "dataset_version": "9461caf6458e09fa69879438f6984b1d9ad4ffe9", "metadata_sources": {"key_source_map": {}, "sources": [{"source_name": "metalad_core", "source_version": "1", "source_parameter": {}, "source_time": 1681820207.486501, "agent_email": "m.szczepanik@fz-juelich.de", "agent_name": "Micha\u0142 Szczepanik"}]}, "path": "MRI_raw_data/Treatment/P56/physio/GV_T3_12_1_1_8_20191008_102322/GV_T3_12_1_1_8_20191008_102322.PHYSWAV.7.ASC", "contentbytesize": 23488, "name": "GV_T3_12_1_1_8_20191008_102322.PHYSWAV.7.ASC"}, {"type": "file", "dataset_id": "f1a7ead6-a448-4c29-aad5-921e59db6aba", "dataset_version": "9461caf6458e09fa69879438f6984b1d9ad4ffe9", "metadata_sources": {"key_source_map": {}, "sources": [{"source_name": "metalad_core", "source_version": "1", "source_parameter": {}, "source_time": 1681820207.489138, "agent_email": "m.szczepanik@fz-juelich.de", "agent_name": "Micha\u0142 Szczepanik"}]}, "path": "MRI_raw_data/Treatment/P56/physio/GV_T3_12_1_1_8_20191008_102322/GV_T3_12_1_1_8_20191008_102322.PHYSWAV.8.I32", "contentbytesize": 9680896, "name": "GV_T3_12_1_1_8_20191008_102322.PHYSWAV.8.I32"}, {"type": "file", "dataset_id": "f1a7ead6-a448-4c29-aad5-921e59db6aba", "dataset_version": "9461caf6458e09fa69879438f6984b1d9ad4ffe9", "metadata_sources": {"key_source_map": {}, "sources": [{"source_name": "metalad_core", "source_version": "1", "source_parameter": {}, "source_time": 1681820207.4891348, "agent_email": "m.szczepanik@fz-juelich.de", "agent_name": "Micha\u0142 Szczepanik"}]}, "path": "MRI_raw_data/Treatment/P56/physio/GV_T3_12_1_1_8_20191008_102322/GV_T3_12_1_1_8_20191008_102322.PHYSWAV.7.I32", "contentbytesize": 768000, "name": "GV_T3_12_1_1_8_20191008_102322.PHYSWAV.7.I32"}, {"type": "file", "dataset_id": "f1a7ead6-a448-4c29-aad5-921e59db6aba", "dataset_version": "9461caf6458e09fa69879438f6984b1d9ad4ffe9", "metadata_sources": {"key_source_map": {}, "sources": [{"source_name": "metalad_core", "source_version": "1", "source_parameter": {}, "source_time": 1681820207.4893293, "agent_email": "m.szczepanik@fz-juelich.de", "agent_name": "Micha\u0142 Szczepanik"}]}, "path": "MRI_raw_data/Treatment/P56/physio/GV_T3_12_1_1_8_20191008_102322/GV_T3_12_1_1_8_20191008_102322.PHYSWAV.8.ASC", "contentbytesize": 191028, "name": "GV_T3_12_1_1_8_20191008_102322.PHYSWAV.8.ASC"}, {"type": "file", "dataset_id": "f1a7ead6-a448-4c29-aad5-921e59db6aba", "dataset_version": "9461caf6458e09fa69879438f6984b1d9ad4ffe9", "metadata_sources": {"key_source_map": {}, "sources": [{"source_name": "metalad_core", "source_version": "1", "source_parameter": {}, "source_time": 1681820207.4930701, "agent_email": "m.szczepanik@fz-juelich.de", "agent_name": "Micha\u0142 Szczepanik"}]}, "path": "MRI_raw_data/Treatment/P56/physio/GV_T3_12_1_1_8_20191008_102322/GV_T3_12_1_1_8_20191008_102322.PHYSWAV.9.I32", "contentbytesize": 13824000, "name": "GV_T3_12_1_1_8_20191008_102322.PHYSWAV.9.I32"}, {"type": "file", "dataset_id": "f1a7ead6-a448-4c29-aad5-921e59db6aba", "dataset_version": "9461caf6458e09fa69879438f6984b1d9ad4ffe9", "metadata_sources": {"key_source_map": {}, "sources": [{"source_name": "metalad_core", "source_version": "1", "source_parameter": {}, "source_time": 1681820207.500049, "agent_email": "m.szczepanik@fz-juelich.de", "agent_name": "Micha\u0142 Szczepanik"}]}, "path": "MRI_raw_data/Treatment/P56/physio/GV_T3_12_1_1_8_20191008_102322/GV_T3_12_1_1_8_20191008_102322.PRO.TXT", "contentbytesize": 176, "name": "GV_T3_12_1_1_8_20191008_102322.PRO.TXT"}, {"type": "file", "dataset_id": "f1a7ead6-a448-4c29-aad5-921e59db6aba", "dataset_version": "9461caf6458e09fa69879438f6984b1d9ad4ffe9", "metadata_sources": {"key_source_map": {}, "sources": [{"source_name": "metalad_core", "source_version": "1", "source_parameter": {}, "source_time": 1681820207.501982, "agent_email": "m.szczepanik@fz-juelich.de", "agent_name": "Micha\u0142 Szczepanik"}]}, "path": "MRI_raw_data/Treatment/P56/physio/GV_T3_12_1_1_8_20191008_102322/GV_T3_12_1_1_8_20191008_102322.SCR.WMF", "contentbytesize": 108360, "name": "GV_T3_12_1_1_8_20191008_102322.SCR.WMF"}, {"type": "file", "dataset_id": "f1a7ead6-a448-4c29-aad5-921e59db6aba", "dataset_version": "9461caf6458e09fa69879438f6984b1d9ad4ffe9", "metadata_sources": {"key_source_map": {}, "sources": [{"source_name": "metalad_core", "source_version": "1", "source_parameter": {}, "source_time": 1681820207.5037313, "agent_email": "m.szczepanik@fz-juelich.de", "agent_name": "Micha\u0142 Szczepanik"}]}, "path": "MRI_raw_data/Treatment/P56/physio/GV_T3_12_1_1_8_20191008_102322/GV_T3_12_1_1_8_20191008_102322.SCR.JPG", "contentbytesize": 354486, "name": "GV_T3_12_1_1_8_20191008_102322.SCR.JPG"}], "path": "MRI_raw_data/Treatment/P56/physio/GV_T3_12_1_1_8_20191008_102322", "name": "GV_T3_12_1_1_8_20191008_102322"}