{"type": "directory", "dataset_id": "f1a7ead6-a448-4c29-aad5-921e59db6aba", "dataset_version": "9461caf6458e09fa69879438f6984b1d9ad4ffe9", "children": [{"type": "file", "dataset_id": "f1a7ead6-a448-4c29-aad5-921e59db6aba", "dataset_version": "9461caf6458e09fa69879438f6984b1d9ad4ffe9", "metadata_sources": {"key_source_map": {}, "sources": [{"source_name": "metalad_core", "source_version": "1", "source_parameter": {}, "source_time": 1681820201.7490842, "agent_email": "m.szczepanik@fz-juelich.de", "agent_name": "Micha\u0142 Szczepanik"}]}, "path": "MRI_raw_data/Treatment/P28/GV_T3_16_1_1_4_20191015_092459/8/AdjStatePerScan", "contentbytesize": 893, "name": "AdjStatePerScan"}, {"type": "file", "dataset_id": "f1a7ead6-a448-4c29-aad5-921e59db6aba", "dataset_version": "9461caf6458e09fa69879438f6984b1d9ad4ffe9", "metadata_sources": {"key_source_map": {}, "sources": [{"source_name": "metalad_core", "source_version": "1", "source_parameter": {}, "source_time": 1681820201.755402, "agent_email": "m.szczepanik@fz-juelich.de", "agent_name": "Micha\u0142 Szczepanik"}]}, "path": "MRI_raw_data/Treatment/P28/GV_T3_16_1_1_4_20191015_092459/8/fid", "contentbytesize": 101427200, "name": "fid"}, {"type": "file", "dataset_id": "f1a7ead6-a448-4c29-aad5-921e59db6aba", "dataset_version": "9461caf6458e09fa69879438f6984b1d9ad4ffe9", "metadata_sources": {"key_source_map": {}, "sources": [{"source_name": "metalad_core", "source_version": "1", "source_parameter": {}, "source_time": 1681820201.75182, "agent_email": "m.szczepanik@fz-juelich.de", "agent_name": "Micha\u0142 Szczepanik"}]}, "path": "MRI_raw_data/Treatment/P28/GV_T3_16_1_1_4_20191015_092459/8/configscan", "contentbytesize": 7062, "name": "configscan"}, {"type": "directory", "name": "pdata", "path": "MRI_raw_data/Treatment/P28/GV_T3_16_1_1_4_20191015_092459/8/pdata", "dataset_id": "f1a7ead6-a448-4c29-aad5-921e59db6aba", "dataset_version": "9461caf6458e09fa69879438f6984b1d9ad4ffe9"}, {"type": "file", "dataset_id": "f1a7ead6-a448-4c29-aad5-921e59db6aba", "dataset_version": "9461caf6458e09fa69879438f6984b1d9ad4ffe9", "metadata_sources": {"key_source_map": {}, "sources": [{"source_name": "metalad_core", "source_version": "1", "source_parameter": {}, "source_time": 1681820201.7660189, "agent_email": "m.szczepanik@fz-juelich.de", "agent_name": "Micha\u0142 Szczepanik"}]}, "path": "MRI_raw_data/Treatment/P28/GV_T3_16_1_1_4_20191015_092459/8/method", "contentbytesize": 64572, "name": "method"}, {"type": "file", "dataset_id": "f1a7ead6-a448-4c29-aad5-921e59db6aba", "dataset_version": "9461caf6458e09fa69879438f6984b1d9ad4ffe9", "metadata_sources": {"key_source_map": {}, "sources": [{"source_name": "metalad_core", "source_version": "1", "source_parameter": {}, "source_time": 1681820201.771785, "agent_email": "m.szczepanik@fz-juelich.de", "agent_name": "Micha\u0142 Szczepanik"}]}, "path": "MRI_raw_data/Treatment/P28/GV_T3_16_1_1_4_20191015_092459/8/acqp", "contentbytesize": 21497, "name": "acqp"}, {"type": "file", "dataset_id": "f1a7ead6-a448-4c29-aad5-921e59db6aba", "dataset_version": "9461caf6458e09fa69879438f6984b1d9ad4ffe9", "metadata_sources": {"key_source_map": {}, "sources": [{"source_name": "metalad_core", "source_version": "1", "source_parameter": {}, "source_time": 1681820201.7805605, "agent_email": "m.szczepanik@fz-juelich.de", "agent_name": "Micha\u0142 Szczepanik"}]}, "path": "MRI_raw_data/Treatment/P28/GV_T3_16_1_1_4_20191015_092459/8/uxnmr.par", "contentbytesize": 26513, "name": "uxnmr.par"}, {"type": "file", "dataset_id": "f1a7ead6-a448-4c29-aad5-921e59db6aba", "dataset_version": "9461caf6458e09fa69879438f6984b1d9ad4ffe9", "metadata_sources": {"key_source_map": {}, "sources": [{"source_name": "metalad_core", "source_version": "1", "source_parameter": {}, "source_time": 1681820201.7947931, "agent_email": "m.szczepanik@fz-juelich.de", "agent_name": "Micha\u0142 Szczepanik"}]}, "path": "MRI_raw_data/Treatment/P28/GV_T3_16_1_1_4_20191015_092459/8/visu_pars", "contentbytesize": 54115, "name": "visu_pars"}, {"type": "file", "dataset_id": "f1a7ead6-a448-4c29-aad5-921e59db6aba", "dataset_version": "9461caf6458e09fa69879438f6984b1d9ad4ffe9", "metadata_sources": {"key_source_map": {}, "sources": [{"source_name": "metalad_core", "source_version": "1", "source_parameter": {}, "source_time": 1681820201.7852826, "agent_email": "m.szczepanik@fz-juelich.de", "agent_name": "Micha\u0142 Szczepanik"}]}, "path": "MRI_raw_data/Treatment/P28/GV_T3_16_1_1_4_20191015_092459/8/pulseprogram", "contentbytesize": 42479, "name": "pulseprogram"}, {"type": "file", "dataset_id": "f1a7ead6-a448-4c29-aad5-921e59db6aba", "dataset_version": "9461caf6458e09fa69879438f6984b1d9ad4ffe9", "metadata_sources": {"key_source_map": {}, "sources": [{"source_name": "metalad_core", "source_version": "1", "source_parameter": {}, "source_time": 1681820201.788255, "agent_email": "m.szczepanik@fz-juelich.de", "agent_name": "Micha\u0142 Szczepanik"}]}, "path": "MRI_raw_data/Treatment/P28/GV_T3_16_1_1_4_20191015_092459/8/spnam41", "contentbytesize": 57874, "name": "spnam41"}, {"type": "file", "dataset_id": "f1a7ead6-a448-4c29-aad5-921e59db6aba", "dataset_version": "9461caf6458e09fa69879438f6984b1d9ad4ffe9", "metadata_sources": {"key_source_map": {}, "sources": [{"source_name": "metalad_core", "source_version": "1", "source_parameter": {}, "source_time": 1681820201.7884042, "agent_email": "m.szczepanik@fz-juelich.de", "agent_name": "Micha\u0142 Szczepanik"}]}, "path": "MRI_raw_data/Treatment/P28/GV_T3_16_1_1_4_20191015_092459/8/specpar", "contentbytesize": 937, "name": "specpar"}, {"type": "file", "dataset_id": "f1a7ead6-a448-4c29-aad5-921e59db6aba", "dataset_version": "9461caf6458e09fa69879438f6984b1d9ad4ffe9", "metadata_sources": {"key_source_map": {}, "sources": [{"source_name": "metalad_core", "source_version": "1", "source_parameter": {}, "source_time": 1681820201.7905314, "agent_email": "m.szczepanik@fz-juelich.de", "agent_name": "Micha\u0142 Szczepanik"}]}, "path": "MRI_raw_data/Treatment/P28/GV_T3_16_1_1_4_20191015_092459/8/uxnmr.info", "contentbytesize": 7437, "name": "uxnmr.info"}], "path": "MRI_raw_data/Treatment/P28/GV_T3_16_1_1_4_20191015_092459/8", "name": "8"}