{"type": "directory", "dataset_id": "f1a7ead6-a448-4c29-aad5-921e59db6aba", "dataset_version": "9461caf6458e09fa69879438f6984b1d9ad4ffe9", "children": [{"type": "file", "dataset_id": "f1a7ead6-a448-4c29-aad5-921e59db6aba", "dataset_version": "9461caf6458e09fa69879438f6984b1d9ad4ffe9", "metadata_sources": {"key_source_map": {}, "sources": [{"source_name": "metalad_core", "source_version": "1", "source_parameter": {}, "source_time": 1681820208.205341, "agent_email": "m.szczepanik@fz-juelich.de", "agent_name": "Micha\u0142 Szczepanik"}]}, "path": "MRI_raw_data/Treatment/P7/GV_T3_12_1_1_4_20190820_090634/9/fid", "contentbytesize": 101427200, "name": "fid"}, {"type": "file", "dataset_id": "f1a7ead6-a448-4c29-aad5-921e59db6aba", "dataset_version": "9461caf6458e09fa69879438f6984b1d9ad4ffe9", "metadata_sources": {"key_source_map": {}, "sources": [{"source_name": "metalad_core", "source_version": "1", "source_parameter": {}, "source_time": 1681820208.2045887, "agent_email": "m.szczepanik@fz-juelich.de", "agent_name": "Micha\u0142 Szczepanik"}]}, "path": "MRI_raw_data/Treatment/P7/GV_T3_12_1_1_4_20190820_090634/9/AdjStatePerScan", "contentbytesize": 893, "name": "AdjStatePerScan"}, {"type": "directory", "name": "pdata", "path": "MRI_raw_data/Treatment/P7/GV_T3_12_1_1_4_20190820_090634/9/pdata", "dataset_id": "f1a7ead6-a448-4c29-aad5-921e59db6aba", "dataset_version": "9461caf6458e09fa69879438f6984b1d9ad4ffe9"}, {"type": "file", "dataset_id": "f1a7ead6-a448-4c29-aad5-921e59db6aba", "dataset_version": "9461caf6458e09fa69879438f6984b1d9ad4ffe9", "metadata_sources": {"key_source_map": {}, "sources": [{"source_name": "metalad_core", "source_version": "1", "source_parameter": {}, "source_time": 1681820208.2068453, "agent_email": "m.szczepanik@fz-juelich.de", "agent_name": "Micha\u0142 Szczepanik"}]}, "path": "MRI_raw_data/Treatment/P7/GV_T3_12_1_1_4_20190820_090634/9/configscan", "contentbytesize": 7062, "name": "configscan"}, {"type": "file", "dataset_id": "f1a7ead6-a448-4c29-aad5-921e59db6aba", "dataset_version": "9461caf6458e09fa69879438f6984b1d9ad4ffe9", "metadata_sources": {"key_source_map": {}, "sources": [{"source_name": "metalad_core", "source_version": "1", "source_parameter": {}, "source_time": 1681820208.2103505, "agent_email": "m.szczepanik@fz-juelich.de", "agent_name": "Micha\u0142 Szczepanik"}]}, "path": "MRI_raw_data/Treatment/P7/GV_T3_12_1_1_4_20190820_090634/9/acqp", "contentbytesize": 21432, "name": "acqp"}, {"type": "file", "dataset_id": "f1a7ead6-a448-4c29-aad5-921e59db6aba", "dataset_version": "9461caf6458e09fa69879438f6984b1d9ad4ffe9", "metadata_sources": {"key_source_map": {}, "sources": [{"source_name": "metalad_core", "source_version": "1", "source_parameter": {}, "source_time": 1681820208.2129416, "agent_email": "m.szczepanik@fz-juelich.de", "agent_name": "Micha\u0142 Szczepanik"}]}, "path": "MRI_raw_data/Treatment/P7/GV_T3_12_1_1_4_20190820_090634/9/method", "contentbytesize": 64567, "name": "method"}, {"type": "file", "dataset_id": "f1a7ead6-a448-4c29-aad5-921e59db6aba", "dataset_version": "9461caf6458e09fa69879438f6984b1d9ad4ffe9", "metadata_sources": {"key_source_map": {}, "sources": [{"source_name": "metalad_core", "source_version": "1", "source_parameter": {}, "source_time": 1681820208.225714, "agent_email": "m.szczepanik@fz-juelich.de", "agent_name": "Micha\u0142 Szczepanik"}]}, "path": "MRI_raw_data/Treatment/P7/GV_T3_12_1_1_4_20190820_090634/9/specpar", "contentbytesize": 937, "name": "specpar"}, {"type": "file", "dataset_id": "f1a7ead6-a448-4c29-aad5-921e59db6aba", "dataset_version": "9461caf6458e09fa69879438f6984b1d9ad4ffe9", "metadata_sources": {"key_source_map": {}, "sources": [{"source_name": "metalad_core", "source_version": "1", "source_parameter": {}, "source_time": 1681820208.2279744, "agent_email": "m.szczepanik@fz-juelich.de", "agent_name": "Micha\u0142 Szczepanik"}]}, "path": "MRI_raw_data/Treatment/P7/GV_T3_12_1_1_4_20190820_090634/9/spnam41", "contentbytesize": 57874, "name": "spnam41"}, {"type": "file", "dataset_id": "f1a7ead6-a448-4c29-aad5-921e59db6aba", "dataset_version": "9461caf6458e09fa69879438f6984b1d9ad4ffe9", "metadata_sources": {"key_source_map": {}, "sources": [{"source_name": "metalad_core", "source_version": "1", "source_parameter": {}, "source_time": 1681820208.22823, "agent_email": "m.szczepanik@fz-juelich.de", "agent_name": "Micha\u0142 Szczepanik"}]}, "path": "MRI_raw_data/Treatment/P7/GV_T3_12_1_1_4_20190820_090634/9/pulseprogram", "contentbytesize": 42479, "name": "pulseprogram"}, {"type": "file", "dataset_id": "f1a7ead6-a448-4c29-aad5-921e59db6aba", "dataset_version": "9461caf6458e09fa69879438f6984b1d9ad4ffe9", "metadata_sources": {"key_source_map": {}, "sources": [{"source_name": "metalad_core", "source_version": "1", "source_parameter": {}, "source_time": 1681820208.235007, "agent_email": "m.szczepanik@fz-juelich.de", "agent_name": "Micha\u0142 Szczepanik"}]}, "path": "MRI_raw_data/Treatment/P7/GV_T3_12_1_1_4_20190820_090634/9/uxnmr.info", "contentbytesize": 7437, "name": "uxnmr.info"}, {"type": "file", "dataset_id": "f1a7ead6-a448-4c29-aad5-921e59db6aba", "dataset_version": "9461caf6458e09fa69879438f6984b1d9ad4ffe9", "metadata_sources": {"key_source_map": {}, "sources": [{"source_name": "metalad_core", "source_version": "1", "source_parameter": {}, "source_time": 1681820208.235745, "agent_email": "m.szczepanik@fz-juelich.de", "agent_name": "Micha\u0142 Szczepanik"}]}, "path": "MRI_raw_data/Treatment/P7/GV_T3_12_1_1_4_20190820_090634/9/uxnmr.par", "contentbytesize": 26513, "name": "uxnmr.par"}, {"type": "file", "dataset_id": "f1a7ead6-a448-4c29-aad5-921e59db6aba", "dataset_version": "9461caf6458e09fa69879438f6984b1d9ad4ffe9", "metadata_sources": {"key_source_map": {}, "sources": [{"source_name": "metalad_core", "source_version": "1", "source_parameter": {}, "source_time": 1681820208.2401822, "agent_email": "m.szczepanik@fz-juelich.de", "agent_name": "Micha\u0142 Szczepanik"}]}, "path": "MRI_raw_data/Treatment/P7/GV_T3_12_1_1_4_20190820_090634/9/visu_pars", "contentbytesize": 54022, "name": "visu_pars"}], "path": "MRI_raw_data/Treatment/P7/GV_T3_12_1_1_4_20190820_090634/9", "name": "9"}