{"type": "directory", "dataset_id": "3ef452bb-43c4-460a-9fbf-120f13dbf78e", "dataset_version": "931fe5f151fbe1aa2ae8ac35efc5ec94c0a671a7", "children": [{"type": "file", "dataset_id": "3ef452bb-43c4-460a-9fbf-120f13dbf78e", "dataset_version": "931fe5f151fbe1aa2ae8ac35efc5ec94c0a671a7", "metadata_sources": {"key_source_map": {}, "sources": [{"source_name": "metalad_core", "source_version": "1", "source_parameter": {}, "source_time": 1681829448.943599, "agent_email": "m.szczepanik@fz-juelich.de", "agent_name": "Micha\u0142 Szczepanik"}]}, "path": "inputs/MRI_proc_data/P42/Treatment_C3a/physio/GV_T3_12_1_1_7_20190924_160057/GV_T3_12_1_1_7_20190924_160057.PHYSWAV.5.I32", "contentbytesize": 5775360, "name": "GV_T3_12_1_1_7_20190924_160057.PHYSWAV.5.I32"}, {"type": "file", "dataset_id": "3ef452bb-43c4-460a-9fbf-120f13dbf78e", "dataset_version": "931fe5f151fbe1aa2ae8ac35efc5ec94c0a671a7", "metadata_sources": {"key_source_map": {}, "sources": [{"source_name": "metalad_core", "source_version": "1", "source_parameter": {}, "source_time": 1681829448.9471722, "agent_email": "m.szczepanik@fz-juelich.de", "agent_name": "Micha\u0142 Szczepanik"}]}, "path": "inputs/MRI_proc_data/P42/Treatment_C3a/physio/GV_T3_12_1_1_7_20190924_160057/GV_T3_12_1_1_7_20190924_160057.10S.ASC", "contentbytesize": 12423, "name": "GV_T3_12_1_1_7_20190924_160057.10S.ASC"}, {"type": "file", "dataset_id": "3ef452bb-43c4-460a-9fbf-120f13dbf78e", "dataset_version": "931fe5f151fbe1aa2ae8ac35efc5ec94c0a671a7", "metadata_sources": {"key_source_map": {}, "sources": [{"source_name": "metalad_core", "source_version": "1", "source_parameter": {}, "source_time": 1681829448.9421895, "agent_email": "m.szczepanik@fz-juelich.de", "agent_name": "Micha\u0142 Szczepanik"}]}, "path": "inputs/MRI_proc_data/P42/Treatment_C3a/physio/GV_T3_12_1_1_7_20190924_160057/GV_T3_12_1_1_7_20190924_160057.PHYSWAV.6.ASC", "contentbytesize": 95349, "name": "GV_T3_12_1_1_7_20190924_160057.PHYSWAV.6.ASC"}, {"type": "file", "dataset_id": "3ef452bb-43c4-460a-9fbf-120f13dbf78e", "dataset_version": "931fe5f151fbe1aa2ae8ac35efc5ec94c0a671a7", "metadata_sources": {"key_source_map": {}, "sources": [{"source_name": "metalad_core", "source_version": "1", "source_parameter": {}, "source_time": 1681829448.942306, "agent_email": "m.szczepanik@fz-juelich.de", "agent_name": "Micha\u0142 Szczepanik"}]}, "path": "inputs/MRI_proc_data/P42/Treatment_C3a/physio/GV_T3_12_1_1_7_20190924_160057/GV_T3_12_1_1_7_20190924_160057.PHYSWAV.1.I32", "contentbytesize": 335872, "name": "GV_T3_12_1_1_7_20190924_160057.PHYSWAV.1.I32"}, {"type": "file", "dataset_id": "3ef452bb-43c4-460a-9fbf-120f13dbf78e", "dataset_version": "931fe5f151fbe1aa2ae8ac35efc5ec94c0a671a7", "metadata_sources": {"key_source_map": {}, "sources": [{"source_name": "metalad_core", "source_version": "1", "source_parameter": {}, "source_time": 1681829448.9493253, "agent_email": "m.szczepanik@fz-juelich.de", "agent_name": "Micha\u0142 Szczepanik"}]}, "path": "inputs/MRI_proc_data/P42/Treatment_C3a/physio/GV_T3_12_1_1_7_20190924_160057/GV_T3_12_1_1_7_20190924_160057.PHYSWAV.4.I32", "contentbytesize": 286720, "name": "GV_T3_12_1_1_7_20190924_160057.PHYSWAV.4.I32"}, {"type": "file", "dataset_id": "3ef452bb-43c4-460a-9fbf-120f13dbf78e", "dataset_version": "931fe5f151fbe1aa2ae8ac35efc5ec94c0a671a7", "metadata_sources": {"key_source_map": {}, "sources": [{"source_name": "metalad_core", "source_version": "1", "source_parameter": {}, "source_time": 1681829448.9593084, "agent_email": "m.szczepanik@fz-juelich.de", "agent_name": "Micha\u0142 Szczepanik"}]}, "path": "inputs/MRI_proc_data/P42/Treatment_C3a/physio/GV_T3_12_1_1_7_20190924_160057/GV_T3_12_1_1_7_20190924_160057.PRO.TXT", "contentbytesize": 176, "name": "GV_T3_12_1_1_7_20190924_160057.PRO.TXT"}, {"type": "file", "dataset_id": "3ef452bb-43c4-460a-9fbf-120f13dbf78e", "dataset_version": "931fe5f151fbe1aa2ae8ac35efc5ec94c0a671a7", "metadata_sources": {"key_source_map": {}, "sources": [{"source_name": "metalad_core", "source_version": "1", "source_parameter": {}, "source_time": 1681829448.9606867, "agent_email": "m.szczepanik@fz-juelich.de", "agent_name": "Micha\u0142 Szczepanik"}]}, "path": "inputs/MRI_proc_data/P42/Treatment_C3a/physio/GV_T3_12_1_1_7_20190924_160057/GV_T3_12_1_1_7_20190924_160057.PHYSWAV.6.I32", "contentbytesize": 2527232, "name": "GV_T3_12_1_1_7_20190924_160057.PHYSWAV.6.I32"}, {"type": "file", "dataset_id": "3ef452bb-43c4-460a-9fbf-120f13dbf78e", "dataset_version": "931fe5f151fbe1aa2ae8ac35efc5ec94c0a671a7", "metadata_sources": {"key_source_map": {}, "sources": [{"source_name": "metalad_core", "source_version": "1", "source_parameter": {}, "source_time": 1681829448.9492936, "agent_email": "m.szczepanik@fz-juelich.de", "agent_name": "Micha\u0142 Szczepanik"}]}, "path": "inputs/MRI_proc_data/P42/Treatment_C3a/physio/GV_T3_12_1_1_7_20190924_160057/GV_T3_12_1_1_7_20190924_160057.PHYSWAV.2.I32", "contentbytesize": 1536000, "name": "GV_T3_12_1_1_7_20190924_160057.PHYSWAV.2.I32"}, {"type": "file", "dataset_id": "3ef452bb-43c4-460a-9fbf-120f13dbf78e", "dataset_version": "931fe5f151fbe1aa2ae8ac35efc5ec94c0a671a7", "metadata_sources": {"key_source_map": {}, "sources": [{"source_name": "metalad_core", "source_version": "1", "source_parameter": {}, "source_time": 1681829448.9580674, "agent_email": "m.szczepanik@fz-juelich.de", "agent_name": "Micha\u0142 Szczepanik"}]}, "path": "inputs/MRI_proc_data/P42/Treatment_C3a/physio/GV_T3_12_1_1_7_20190924_160057/GV_T3_12_1_1_7_20190924_160057.SCR.JPG", "contentbytesize": 354486, "name": "GV_T3_12_1_1_7_20190924_160057.SCR.JPG"}, {"type": "file", "dataset_id": "3ef452bb-43c4-460a-9fbf-120f13dbf78e", "dataset_version": "931fe5f151fbe1aa2ae8ac35efc5ec94c0a671a7", "metadata_sources": {"key_source_map": {}, "sources": [{"source_name": "metalad_core", "source_version": "1", "source_parameter": {}, "source_time": 1681829448.9631026, "agent_email": "m.szczepanik@fz-juelich.de", "agent_name": "Micha\u0142 Szczepanik"}]}, "path": "inputs/MRI_proc_data/P42/Treatment_C3a/physio/GV_T3_12_1_1_7_20190924_160057/GV_T3_12_1_1_7_20190924_160057.SCR.WMF", "contentbytesize": 104156, "name": "GV_T3_12_1_1_7_20190924_160057.SCR.WMF"}, {"type": "file", "dataset_id": "3ef452bb-43c4-460a-9fbf-120f13dbf78e", "dataset_version": "931fe5f151fbe1aa2ae8ac35efc5ec94c0a671a7", "metadata_sources": {"key_source_map": {}, "sources": [{"source_name": "metalad_core", "source_version": "1", "source_parameter": {}, "source_time": 1681829448.9734073, "agent_email": "m.szczepanik@fz-juelich.de", "agent_name": "Micha\u0142 Szczepanik"}]}, "path": "inputs/MRI_proc_data/P42/Treatment_C3a/physio/GV_T3_12_1_1_7_20190924_160057/GV_T3_12_1_1_7_20190924_160057.PHYSWAV.7.I32", "contentbytesize": 13840384, "name": "GV_T3_12_1_1_7_20190924_160057.PHYSWAV.7.I32"}], "path": "inputs/MRI_proc_data/P42/Treatment_C3a/physio/GV_T3_12_1_1_7_20190924_160057", "name": "GV_T3_12_1_1_7_20190924_160057"}